PyRVC.cp310-win_amd64.pyd
PyRVC.pdb
rvctesta-1.7.0.dist-info/METADATA
rvctesta-1.7.0.dist-info/WHEEL
rvctesta-1.7.0.dist-info/top_level.txt
rvctesta-1.7.0.dist-info/RECORD
